round2/__init__.py
round2/round2.cp39-win_amd64.pyd
round2/round2.py
round2-0.0.4.dist-info/LICENSE
round2-0.0.4.dist-info/METADATA
round2-0.0.4.dist-info/WHEEL
round2-0.0.4.dist-info/top_level.txt
round2-0.0.4.dist-info/RECORD
