Metadata-Version: 2.1
Name: round2
Version: 0.0.4
Summary: Round half away from zero.
Home-page: https://github.com/MrThearMan/round2
Author: Matti Lamppu
Author-email: lamppu.matti.akseli@gmail.com
License: UNKNOWN
Project-URL: Bug Tracker, https://github.com/MrThearMan/round2/issues
Platform: UNKNOWN
Classifier: Programming Language :: Python :: 3
Classifier: License :: OSI Approved :: MIT License
Classifier: Operating System :: OS Independent
Requires-Python: >=3.6
License-File: LICENSE
